src/botpackage/__init__.py
src/botpackage/commandsModule/__init__.py
src/botpackage/commandsModule/commands.py
src/botpackage/database/__init__.py
src/botpackage/database/db.py
src/botpackage/enums/__init__.py
src/botpackage/enums/enums.py
src/botpackage/messages/__init__.py
src/botpackage/messages/descriptions.py
src/botpackage/messages/messages.py
src/botpackage/models/__init__.py
src/botpackage/models/base.py
src/botpackage/models/episode.py
src/botpackage/models/playstate.py
src/botpackage/models/podcasts.py
src/botpackage/models/subscription.py
src/botpackage/models/user.py
src/botpackage/rssreader/__init__.py
src/botpackage/rssreader/reader.py
src/botpackage/utils/__init__.py
src/botpackage/utils/converters.py
src/botpackage/utils/customAudio.py
src/botpackage/utils/utils.py
src/botpackage/vaultModule/__init__.py
src/botpackage/vaultModule/vault.py
tests/test_commands.py
tests/test_converters.py
tests/test_customAudio.py
tests/test_db.py
tests/test_reader.py
tests/test_utils.py
tests/test_vault.py
podcastbotdiscord-0.1.2.dist-info/METADATA
podcastbotdiscord-0.1.2.dist-info/WHEEL
podcastbotdiscord-0.1.2.dist-info/licenses/LICENSE
podcastbotdiscord-0.1.2.dist-info/RECORD
